rostaingchain/__init__.py
rostaingchain/core.py
rostaingchain/embeddings.py
rostaingchain/llm_engine.py
rostaingchain/loaders.py
rostaingchain/security.py
rostaingchain/vector_store.py
rostaingchain/watcher.py
rostaingchain/__pycache__/__init__.cpython-312.pyc
rostaingchain/__pycache__/core.cpython-312.pyc
rostaingchain/__pycache__/embeddings.cpython-312.pyc
rostaingchain/__pycache__/llm_engine.cpython-312.pyc
rostaingchain/__pycache__/loaders.cpython-312.pyc
rostaingchain/__pycache__/security.cpython-312.pyc
rostaingchain/__pycache__/vector_store.cpython-312.pyc
rostaingchain/__pycache__/watcher.cpython-312.pyc
rostaingchain-0.2.3.dist-info/licenses/LICENSE
rostaingchain-0.2.3.dist-info/METADATA
rostaingchain-0.2.3.dist-info/WHEEL
rostaingchain-0.2.3.dist-info/top_level.txt
rostaingchain-0.2.3.dist-info/RECORD
