Metadata-Version: 2.4
Name: rostaingchain
Version: 0.2.3
Summary: The Ultimate Hybrid RAG Framework: Local/Remote LLMs, Live Watcher, Deep Profiling & Security.
Home-page: https://github.com/Rostaing/rostaingchain
Author: Davila Rostaing
Author-email: rostaingdavila@gmail.com
License: MIT
Classifier: License :: OSI Approved :: MIT License
Classifier: Programming Language :: Python :: 3
Classifier: Programming Language :: Python :: 3.9
Classifier: Programming Language :: Python :: 3.10
Classifier: Operating System :: OS Independent
Classifier: Topic :: Scientific/Engineering :: Artificial Intelligence
License-File: LICENSE
Requires-Dist: langchain
Requires-Dist: langchain-community
Requires-Dist: langchain-core
Requires-Dist: langchain-text-splitters
Requires-Dist: fastembed
Requires-Dist: chromadb
Requires-Dist: pandas
Requires-Dist: numpy
Requires-Dist: watchdog
Requires-Dist: python-dotenv
Requires-Dist: pyttsx3
Provides-Extra: llms
Requires-Dist: langchain-ollama; extra == "llms"
Requires-Dist: langchain-openai; extra == "llms"
Requires-Dist: langchain-anthropic; extra == "llms"
Requires-Dist: langchain-google-genai; extra == "llms"
Requires-Dist: langchain-groq; extra == "llms"
Requires-Dist: langchain-mistralai; extra == "llms"
Requires-Dist: langchain-huggingface; extra == "llms"
Requires-Dist: huggingface-hub; extra == "llms"
Provides-Extra: database
Requires-Dist: sqlalchemy; extra == "database"
Requires-Dist: pymongo; extra == "database"
Requires-Dist: neo4j; extra == "database"
Requires-Dist: psycopg2-binary; extra == "database"
Requires-Dist: pymssql; extra == "database"
Requires-Dist: pymysql; extra == "database"
Requires-Dist: psycopg; extra == "database"
Provides-Extra: vectors
Requires-Dist: faiss-cpu; extra == "vectors"
Requires-Dist: qdrant-client; extra == "vectors"
Requires-Dist: langchain-chroma; extra == "vectors"
Provides-Extra: media
Requires-Dist: openai-whisper; extra == "media"
Requires-Dist: moviepy; extra == "media"
Requires-Dist: soundfile; extra == "media"
Requires-Dist: youtube-transcript-api; extra == "media"
Requires-Dist: pytube; extra == "media"
Requires-Dist: beautifulsoup4; extra == "media"
Requires-Dist: html2text; extra == "media"
Provides-Extra: docs
Requires-Dist: rostaing-ocr; extra == "docs"
Requires-Dist: python-docx; extra == "docs"
Requires-Dist: openpyxl; extra == "docs"
Requires-Dist: python-pptx; extra == "docs"
Requires-Dist: unstructured; extra == "docs"
Provides-Extra: hf
Requires-Dist: hf-xet; extra == "hf"
Requires-Dist: hf-transfer; extra == "hf"
Requires-Dist: sentence-transformers; extra == "hf"
Provides-Extra: all
Requires-Dist: langchain-ollama; extra == "all"
Requires-Dist: langchain-openai; extra == "all"
Requires-Dist: langchain-anthropic; extra == "all"
Requires-Dist: langchain-google-genai; extra == "all"
Requires-Dist: langchain-groq; extra == "all"
Requires-Dist: langchain-mistralai; extra == "all"
Requires-Dist: langchain-huggingface; extra == "all"
Requires-Dist: huggingface-hub; extra == "all"
Requires-Dist: sqlalchemy; extra == "all"
Requires-Dist: pymongo; extra == "all"
Requires-Dist: neo4j; extra == "all"
Requires-Dist: psycopg2-binary; extra == "all"
Requires-Dist: pymssql; extra == "all"
Requires-Dist: pymysql; extra == "all"
Requires-Dist: psycopg; extra == "all"
Requires-Dist: faiss-cpu; extra == "all"
Requires-Dist: qdrant-client; extra == "all"
Requires-Dist: langchain-chroma; extra == "all"
Requires-Dist: openai-whisper; extra == "all"
Requires-Dist: moviepy; extra == "all"
Requires-Dist: soundfile; extra == "all"
Requires-Dist: youtube-transcript-api; extra == "all"
Requires-Dist: pytube; extra == "all"
Requires-Dist: beautifulsoup4; extra == "all"
Requires-Dist: html2text; extra == "all"
Requires-Dist: rostaing-ocr; extra == "all"
Requires-Dist: python-docx; extra == "all"
Requires-Dist: openpyxl; extra == "all"
Requires-Dist: python-pptx; extra == "all"
Requires-Dist: unstructured; extra == "all"
Requires-Dist: hf-xet; extra == "all"
Requires-Dist: hf-transfer; extra == "all"
Requires-Dist: sentence-transformers; extra == "all"
Requires-Dist: cx-oracle; extra == "all"
Dynamic: author
Dynamic: author-email
Dynamic: classifier
Dynamic: description
Dynamic: description-content-type
Dynamic: home-page
Dynamic: license
Dynamic: license-file
Dynamic: provides-extra
Dynamic: requires-dist
Dynamic: summary
